terrajinja/imports/akamai/__init__.py
terrajinja/imports/akamai/py.typed
terrajinja/imports/akamai/_jsii/__init__.py
terrajinja/imports/akamai/_jsii/akamai@0.0.0.jsii.tgz
terrajinja/imports/akamai/appsec_activations/__init__.py
terrajinja/imports/akamai/appsec_advanced_settings_attack_payload_logging/__init__.py
terrajinja/imports/akamai/appsec_advanced_settings_evasive_path_match/__init__.py
terrajinja/imports/akamai/appsec_advanced_settings_logging/__init__.py
terrajinja/imports/akamai/appsec_advanced_settings_pii_learning/__init__.py
terrajinja/imports/akamai/appsec_advanced_settings_pragma_header/__init__.py
terrajinja/imports/akamai/appsec_advanced_settings_prefetch/__init__.py
terrajinja/imports/akamai/appsec_advanced_settings_request_body/__init__.py
terrajinja/imports/akamai/appsec_api_constraints_protection/__init__.py
terrajinja/imports/akamai/appsec_api_request_constraints/__init__.py
terrajinja/imports/akamai/appsec_attack_group/__init__.py
terrajinja/imports/akamai/appsec_bypass_network_lists/__init__.py
terrajinja/imports/akamai/appsec_configuration/__init__.py
terrajinja/imports/akamai/appsec_configuration_rename/__init__.py
terrajinja/imports/akamai/appsec_custom_deny/__init__.py
terrajinja/imports/akamai/appsec_custom_rule/__init__.py
terrajinja/imports/akamai/appsec_custom_rule_action/__init__.py
terrajinja/imports/akamai/appsec_eval/__init__.py
terrajinja/imports/akamai/appsec_eval_group/__init__.py
terrajinja/imports/akamai/appsec_eval_penalty_box/__init__.py
terrajinja/imports/akamai/appsec_eval_rule/__init__.py
terrajinja/imports/akamai/appsec_ip_geo/__init__.py
terrajinja/imports/akamai/appsec_ip_geo_protection/__init__.py
terrajinja/imports/akamai/appsec_malware_policy/__init__.py
terrajinja/imports/akamai/appsec_malware_policy_action/__init__.py
terrajinja/imports/akamai/appsec_malware_policy_actions/__init__.py
terrajinja/imports/akamai/appsec_malware_protection/__init__.py
terrajinja/imports/akamai/appsec_match_target/__init__.py
terrajinja_imports_akamai-5.6.0.dist-info/LICENSE
terrajinja_imports_akamai-5.6.0.dist-info/METADATA
terrajinja_imports_akamai-5.6.0.dist-info/WHEEL
terrajinja_imports_akamai-5.6.0.dist-info/top_level.txt
terrajinja_imports_akamai-5.6.0.dist-info/RECORD
