Metadata-Version: 2.1
Name: terrajinja-imports-akamai
Version: 5.6.0
Summary: Prebuild import for akamai
Home-page: https://gitlab/terrajinja
Author: Terrajinja Team
Author-email: int-terrajinja@schubergphilis.com
License: MIT
Classifier: Development Status :: 4 - Beta
Classifier: Intended Audience :: Developers
Classifier: License :: OSI Approved :: MIT License
Classifier: Natural Language :: English
Classifier: Programming Language :: Python :: 3.11
License-File: LICENSE
Requires-Dist: cdktf >=0.20.3
